functional_cat/__init__.py
functional_cat/data_types.py
functional_cat/interfaces.py
functional_cat/io.py
functional_cat/registry.py
functional_cat/funcs/__init__.py
functional_cat/funcs/dlib/__init__.py
functional_cat/funcs/dlib/detection.py
functional_cat/funcs/glip/__init__.py
functional_cat/funcs/glip/glip.py
functional_cat/funcs/onnx/__init__.py
functional_cat/funcs/onnx/tiny_yolov3.py
functional_cat/funcs/onnx/yolov4.py
functional_cat/funcs/torchvision/__init__.py
functional_cat/funcs/torchvision/detection.py
functional_cat-0.5.1.dist-info/LICENSE
functional_cat-0.5.1.dist-info/METADATA
functional_cat-0.5.1.dist-info/WHEEL
functional_cat-0.5.1.dist-info/top_level.txt
functional_cat-0.5.1.dist-info/RECORD
