Metadata-Version: 2.1
Name: functional-cat
Version: 0.5.1
Summary: Catalog of functions
License: Copyright 2022 Eric O. Korman
Requires-Python: >=3.7
License-File: LICENSE
Requires-Dist: requests
Requires-Dist: Pillow <=9.5.0,>=9.1.0
Requires-Dist: tqdm
Requires-Dist: numpy >=1.23
Provides-Extra: catalog
Requires-Dist: boto3 ; extra == 'catalog'
Requires-Dist: python-dotenv ; extra == 'catalog'
Provides-Extra: dlib
Requires-Dist: dlib ; extra == 'dlib'
Provides-Extra: glip
Requires-Dist: glip-object-detection ; extra == 'glip'
Provides-Extra: onnx
Requires-Dist: onnxruntime >=1.11 ; extra == 'onnx'
Requires-Dist: scipy ; extra == 'onnx'
Provides-Extra: onnx-cpu
Requires-Dist: onnxruntime >=1.11 ; extra == 'onnx-cpu'
Provides-Extra: onnx-gpu
Requires-Dist: onnxruntime-gpu >=1.11 ; extra == 'onnx-gpu'
Provides-Extra: test
Requires-Dist: pytest ; extra == 'test'
Provides-Extra: torch
Requires-Dist: torch >=1.12.0 ; extra == 'torch'
Requires-Dist: torchvision >=0.13.0 ; extra == 'torch'
